guolei_py3_51welink/__init__.py
guolei_py3_51welink/sms.py
guolei_py3_51welink/library/__init__.py
guolei_py3_51welink/library/sms.py
guolei_py3_51welink-2.2.1.dist-info/LICENSE
guolei_py3_51welink-2.2.1.dist-info/METADATA
guolei_py3_51welink-2.2.1.dist-info/WHEEL
guolei_py3_51welink-2.2.1.dist-info/top_level.txt
guolei_py3_51welink-2.2.1.dist-info/RECORD
