Metadata-Version: 2.1
Name: guolei-py3-51welink
Version: 2.2.1
Summary: 微网通联 API
Home-page: https://github.com/guolei19850528/guolei_py3_51welink
Author: guolei
Author-email: 174000902@qq.com
License: MIT
Requires-Python: >=3.0
License-File: LICENSE
Requires-Dist: guolei-py3-requests
Requires-Dist: requests
Requires-Dist: addict
Requires-Dist: retrying
Requires-Dist: jsonschema
